nuaudit_python_sdk/__init__.py
nuaudit_python_sdk/main.py
nuaudit_python_sdk-0.17.1.dist-info/LICENSE
nuaudit_python_sdk-0.17.1.dist-info/METADATA
nuaudit_python_sdk-0.17.1.dist-info/WHEEL
nuaudit_python_sdk-0.17.1.dist-info/top_level.txt
nuaudit_python_sdk-0.17.1.dist-info/RECORD
